odoo/addons/l10n_it_fatturapa_out_stamp/README.rst
odoo/addons/l10n_it_fatturapa_out_stamp/__init__.py
odoo/addons/l10n_it_fatturapa_out_stamp/__manifest__.py
odoo/addons/l10n_it_fatturapa_out_stamp/i18n/it.po
odoo/addons/l10n_it_fatturapa_out_stamp/i18n/l10n_it_fatturapa_out_stamp.pot
odoo/addons/l10n_it_fatturapa_out_stamp/readme/CONTRIBUTORS.rst
odoo/addons/l10n_it_fatturapa_out_stamp/readme/DESCRIPTION.rst
odoo/addons/l10n_it_fatturapa_out_stamp/static/description/icon.png
odoo/addons/l10n_it_fatturapa_out_stamp/static/description/index.html
odoo/addons/l10n_it_fatturapa_out_stamp/wizard/__init__.py
odoo/addons/l10n_it_fatturapa_out_stamp/wizard/wizard_export_fatturapa.py
odoo11_addon_l10n_it_fatturapa_out_stamp-11.0.2.0.0.99.dev2.dist-info/METADATA
odoo11_addon_l10n_it_fatturapa_out_stamp-11.0.2.0.0.99.dev2.dist-info/WHEEL
odoo11_addon_l10n_it_fatturapa_out_stamp-11.0.2.0.0.99.dev2.dist-info/top_level.txt
odoo11_addon_l10n_it_fatturapa_out_stamp-11.0.2.0.0.99.dev2.dist-info/RECORD
